linkedin_games_solver/__init__.py
linkedin_games_solver/cli.py
linkedin_games_solver/queens_solver.py
linkedin_games_solver/solver.py
linkedin_games_solver/tango_solver.py
linkedin_games_solver/web_scraper.py
linkedin_games_solver/zip_solver.py
navid_linkedin_puzzle_solver-1.0.1.dist-info/licenses/LICENSE
navid_linkedin_puzzle_solver-1.0.1.dist-info/METADATA
navid_linkedin_puzzle_solver-1.0.1.dist-info/WHEEL
navid_linkedin_puzzle_solver-1.0.1.dist-info/entry_points.txt
navid_linkedin_puzzle_solver-1.0.1.dist-info/top_level.txt
navid_linkedin_puzzle_solver-1.0.1.dist-info/RECORD
