Metadata-Version: 2.4
Name: navid-linkedin-puzzle-solver
Version: 1.0.1
Summary: Automates solving LinkedIn mini games (Queens, Tango, Zip)
Author-email: Navid Mirzaaghazadeh <mirzaaghazadeh@icloud.com>
License: MIT
Project-URL: Homepage, https://github.com/mirzaaghazadeh/navid-linkedin-puzzle-solver
Project-URL: Repository, https://github.com/mirzaaghazadeh/navid-linkedin-puzzle-solver
Keywords: linkedin,games,solver,selenium,puzzle
Classifier: Programming Language :: Python :: 3
Classifier: License :: OSI Approved :: MIT License
Classifier: Operating System :: OS Independent
Requires-Python: >=3.9
License-File: LICENSE
Requires-Dist: selenium>=4.12
Requires-Dist: webdriver-manager>=4.0
Dynamic: license-file
